fastlcs-1.0.0.dist-info/RECORD
fastlcs-1.0.0.dist-info/top_level.txt
fastlcs-1.0.0.dist-info/WHEEL
fastlcs-1.0.0.dist-info/METADATA
fastlcs/lcs.cpython-310-x86_64-linux-gnu.so
fastlcs/__init__.py
