Metadata-Version: 2.1
Name: fastlcs
Version: 1.0.0
Requires-Dist: pandas
